telepybot/__init__.py
telepybot/helpers/__init__.py
telepybot/helpers/b64.py
telepybot/helpers/public_ip.py
telepybot/main.py
telepybot/models/__init__.py
telepybot/models/pyteledantic.py
telepybot/ssl.py
telepybot/types/__init__.py
telepybot/types/main.py
telepybot/webhook.py
telepybot-0.1.12.dist-info/LICENSE
telepybot-0.1.12.dist-info/WHEEL
telepybot-0.1.12.dist-info/METADATA
telepybot-0.1.12.dist-info/RECORD
