Metadata-Version: 2.1
Name: telepybot
Version: 0.1.12
Summary: A Python class to help you interact with Telegram's bot api.
License: MIT
Author: Federico Giancarelli
Author-email: hello@federicogiancarelli.com
Requires-Python: >=3.9,<4.0
Classifier: License :: OSI Approved :: MIT License
Classifier: Programming Language :: Python :: 3
Classifier: Programming Language :: Python :: 3.9
Classifier: Programming Language :: Python :: 3.10
Requires-Dist: cryptography (>=39.0.2,<40.0.0)
Requires-Dist: pydantic (>=2.4.2,<3.0.0)
Requires-Dist: requests (>=2.31.0,<3.0.0)
